{
    "classname": "AddTask",
    "definitions": {
        "apis": {
            "custom": [
                {
                    "group": "General",
                    "kuid": "cc0d24c614d040fcaa8f21cab4c01c5e",
                    "paramList": [],
                    "propertyKey": "toggle",
                    "pw": {
                        "displayName": "toggle",
                        "uiRepresentation": "Label-Label-Button-Button"
                    },
                    "srcWgtKUID": "j105c524becf4f688cb1a5c01b3015ad",
                    "type": "event"
                }
            ],
            "passthrough": []
        },
        "events": {
            "custom": [],
            "passthrough": []
        },
        "groups": {
            "apis": [
                "General"
            ],
            "events": [],
            "properties": [],
            "widgets": []
        },
        "properties": {
            "custom": [],
            "passthrough": []
        },
        "widgets": {
            "expose": [],
            "passthrough": []
        }
    },
    "namespace": "com.hcl.mario",
    "version": "1.0.0"
}